azure/cognitiveservices/knowledge/qnamaker/__init__.py
azure/cognitiveservices/knowledge/qnamaker/py.typed
azure/cognitiveservices/knowledge/qnamaker/qn_amaker_client.py
azure/cognitiveservices/knowledge/qnamaker/version.py
azure/cognitiveservices/knowledge/qnamaker/models/__init__.py
azure/cognitiveservices/knowledge/qnamaker/models/active_learning_settings_dto.py
azure/cognitiveservices/knowledge/qnamaker/models/active_learning_settings_dto_py3.py
azure/cognitiveservices/knowledge/qnamaker/models/alterations_dto.py
azure/cognitiveservices/knowledge/qnamaker/models/alterations_dto_py3.py
azure/cognitiveservices/knowledge/qnamaker/models/answer_span_request_dto.py
azure/cognitiveservices/knowledge/qnamaker/models/answer_span_request_dto_py3.py
azure/cognitiveservices/knowledge/qnamaker/models/answer_span_response_dto.py
azure/cognitiveservices/knowledge/qnamaker/models/answer_span_response_dto_py3.py
azure/cognitiveservices/knowledge/qnamaker/models/context_dto.py
azure/cognitiveservices/knowledge/qnamaker/models/context_dto_py3.py
azure/cognitiveservices/knowledge/qnamaker/models/create_kb_dto.py
azure/cognitiveservices/knowledge/qnamaker/models/create_kb_dto_py3.py
azure/cognitiveservices/knowledge/qnamaker/models/create_kb_input_dto.py
azure/cognitiveservices/knowledge/qnamaker/models/create_kb_input_dto_py3.py
azure/cognitiveservices/knowledge/qnamaker/models/delete_kb_contents_dto.py
azure/cognitiveservices/knowledge/qnamaker/models/delete_kb_contents_dto_py3.py
azure/cognitiveservices/knowledge/qnamaker/models/endpoint_keys_dto.py
azure/cognitiveservices/knowledge/qnamaker/models/endpoint_keys_dto_py3.py
azure/cognitiveservices/knowledge/qnamaker/models/endpoint_settings_dto.py
azure/cognitiveservices/knowledge/qnamaker/models/endpoint_settings_dto_active_learning.py
azure/cognitiveservices/knowledge/qnamaker/models/endpoint_settings_dto_active_learning_py3.py
azure/cognitiveservices/knowledge/qnamaker/models/endpoint_settings_dto_py3.py
azure_cognitiveservices_knowledge_qnamaker-0.3.1.dist-info/LICENSE
azure_cognitiveservices_knowledge_qnamaker-0.3.1.dist-info/METADATA
azure_cognitiveservices_knowledge_qnamaker-0.3.1.dist-info/WHEEL
azure_cognitiveservices_knowledge_qnamaker-0.3.1.dist-info/top_level.txt
azure_cognitiveservices_knowledge_qnamaker-0.3.1.dist-info/RECORD
